CHANGELOG.md
blablamower/__init__.py
blablamower/__main__.py
blablamower/core/__init__.py
blablamower/core/config.py
blablamower/core/coordinates.py
blablamower/core/lawn.py
blablamower/core/mower.py
blablamower/core/orientation.py
blablamower-1.0.0.dist-info/entry_points.txt
blablamower-1.0.0.dist-info/WHEEL
blablamower-1.0.0.dist-info/METADATA
blablamower-1.0.0.dist-info/RECORD
