Metadata-Version: 2.1
Name: blablamower
Version: 1.0.0
Summary: 
Home-page: https://github.com/renardguill/BlaBlaMower
Author: Guillaume Renard
Author-email: renardguillaume@gmail.com
Requires-Python: >=3.8,<4.0
Classifier: Programming Language :: Python :: 3
Classifier: Programming Language :: Python :: 3.8
Classifier: Programming Language :: Python :: 3.9
Classifier: Programming Language :: Python :: 3.10
Project-URL: Repository, https://github.com/renardguill/BlaBlaMower.git
